cjk_character_count/FontInfoCollector.py
cjk_character_count/__init__.py
cjk_character_count/global_var.py
cjk_character_count/localise.py
cjk_character_count/main.py
cjk_character_count/write_csv.py
cjk_character_count-0.60.dist-info/licenses/LICENSE
cjk_character_count-0.60.dist-info/METADATA
cjk_character_count-0.60.dist-info/WHEEL
cjk_character_count-0.60.dist-info/top_level.txt
cjk_character_count-0.60.dist-info/RECORD
