Metadata-Version: 2.4
Name: cjk-character-count
Version: 0.60
Summary: This is a program that counts the amount of CJK characters based on Unicode ranges and Chinese encoding standards.  
Requires-Python: >=3.13
License-File: LICENSE
Requires-Dist: fonttools>=4.61.1
Requires-Dist: pandas>=2.3.3
Requires-Dist: python-frontmatter>=1.1.0
Requires-Dist: unicode-blocks-py>=17.0.0
Dynamic: license-file
